MANIFEST.in
README.md
pyproject.toml
setup.py
include/stochqn.h
src/stochqn.c
stochqn/__init__.py
stochqn/_logistic.py
stochqn/_optimizers.py
stochqn/pywrapper.pxi
stochqn/tf.py
stochqn/wrapper_double.pyx
stochqn/wrapper_float.pyx
stochqn.egg-info/PKG-INFO
stochqn.egg-info/SOURCES.txt
stochqn.egg-info/dependency_links.txt
stochqn.egg-info/requires.txt
stochqn.egg-info/top_level.txt