Metadata-Version: 1.0
Name: stochqn
Version: 0.2.8.1
Summary: Stochastic limited-memory quasi-Newton optimizers
Home-page: https://github.com/david-cortes/stochQN
Author: David Cortes
Author-email: david.cortes.rivera@gmail.com
License: UNKNOWN
Keywords: optimization,stochastic,quasi-Newton,SQN,adaQN,oLBFGS
Platform: UNKNOWN
